ncu_report-2025.3.1.data/purelib/ncu_report/__init__.py
ncu_report-2025.3.1.data/purelib/ncu_report/_ncu_report.so
ncu_report-2025.3.1.data/purelib/ncu_report/libnvperf_host.so
ncu_report-2025.3.1.dist-info/licenses/LICENSE.rst
ncu_report-2025.3.1.dist-info/METADATA
ncu_report-2025.3.1.dist-info/WHEEL
ncu_report-2025.3.1.dist-info/top_level.txt
ncu_report-2025.3.1.dist-info/RECORD
