Metadata-Version: 2.4
Name: ncu_report
Version: 2025.3.1
Summary: Profiler report Python interface for NVIDIA Nsight Compute
Author-email: NVIDIA Compute Developer Tools <nsight-compute-python@nvidia.com>
Project-URL: Homepage, https://developer.nvidia.com/nsight-compute
Project-URL: Documentation, https://docs.nvidia.com/nsight-compute/PythonReportInterface/index.html
Project-URL: License, https://docs.nvidia.com/nsight-compute/CopyrightAndLicenses/index.html
Keywords: CUDA,performance,profiler
Classifier: License :: Other/Proprietary License
Classifier: Programming Language :: Python
Classifier: Programming Language :: Python :: 3.7
Classifier: Programming Language :: Python :: 3.8
Classifier: Programming Language :: Python :: 3.9
Classifier: Programming Language :: Python :: 3.10
Classifier: Programming Language :: Python :: 3.11
Classifier: Programming Language :: Python :: 3.12
Classifier: Programming Language :: Python :: 3.13
Classifier: Programming Language :: Python :: 3.14
Classifier: Environment :: GPU :: NVIDIA CUDA
Requires-Python: >=3.7
License-File: LICENSE.rst
Dynamic: license-file
